lenskappa/__init__.py
lenskappa/analysis/__init__.py
lenskappa/analysis/analysis.py
lenskappa/analysis/kappa.py
lenskappa/analysis/kappaEnsemble.py
lenskappa/analysis/kappaSet.py
lenskappa/analysis/kappa_analysis.py
lenskappa/analysis/kappa_ensemble_template.json
lenskappa/analysis/kappa_set_template.json
lenskappa/analysis/kappa_template.json
lenskappa/analysis/run_analysis.py
lenskappa/analysis/transformation.py
lenskappa/catalog/__init__.py
lenskappa/catalog/filter.py
lenskappa/catalog/params.py
lenskappa/catalog/utils.py
lenskappa/config/analysis/kappa_template.json
lenskappa/config/base_analysis.json
lenskappa/config/base_config.toml
lenskappa/config/counts.toml
lenskappa/config/hsc.toml
lenskappa/config/hsc_test.toml
lenskappa/counting/__init__.py
lenskappa/counting/counter.py
lenskappa/datasets/__init__.py
lenskappa/datasets/dataset.py
lenskappa/datasets/simulations/simulation.py
lenskappa/datasets/surveys/__init__.py
lenskappa/datasets/surveys/ms/Millennium_distances.txt
lenskappa/datasets/surveys/ms/__init__.py
lenskappa/datasets/surveys/ms/ms.py
lenskappa/datasets/surveys/ms/ms.toml
lenskappa/datasets/surveys/survey.py
lenskappa/kappa_test.py
lenskappa/locations.py
lenskappa/ms_test.py
lenskappa/output/__init__.py
lenskappa/output/output.py
lenskappa/output/parser.py
lenskappa/plugin/__init__.py
lenskappa/test/test.py
lenskappa/test2.py
lenskappa/tests/0029/ms_0_0_sampled.csv
lenskappa/tests/0029/ms_0_4_sampled.csv
lenskappa/tests/0029/ms_1_0_sampled.csv
lenskappa/tests/0029/ms_1_4_sampled.csv
lenskappa/tests/cfht.py
lenskappa/tests/cfht_heinlein.py
lenskappa/tests/cfht_test.csv
lenskappa/tests/initial.py
lenskappa/tests/ms_0_0_sampled.csv
lenskappa/tests/ms_120asec_i23.log
lenskappa/tests/ms_1_0_sampled.csv
lenskappa/tests/ms_heinlein.py
lenskappa/tests/ms_i23_120asec.py
lenskappa/tests/ms_i23_120asec.sh
lenskappa/tests/ms_i24_45asec.py
lenskappa/tests/ms_i24_45asec.sh
lenskappa/tests/ms_weights.sh
lenskappa/tests/output/test_output.py
lenskappa-0.5.8.dist-info/WHEEL
lenskappa-0.5.8.dist-info/entry_points.txt
lenskappa-0.5.8.dist-info/METADATA
lenskappa-0.5.8.dist-info/RECORD
