Metadata-Version: 2.1
Name: lenskappa
Version: 0.5.8
Summary: 
Author: Patrick Wells
Author-email: pwells@ucdavis.edu
Requires-Python: >=3.9,<4.0
Classifier: Programming Language :: Python :: 3
Classifier: Programming Language :: Python :: 3.9
Classifier: Programming Language :: Python :: 3.10
Classifier: Programming Language :: Python :: 3.11
Requires-Dist: Shapely (>=1.8.1,<2.0.0)
Requires-Dist: appdirs (>=1.4.4,<2.0.0)
Requires-Dist: astropy (>=5.0.3,<6.0.0)
Requires-Dist: dask[distributed] (>=2023.3.2,<2024.0.0)
Requires-Dist: heinlein (>=0.4.0,<0.5.0)
Requires-Dist: loguru (>=0.7,<0.8)
Requires-Dist: multiprocess (>=0.70.13,<0.71.0)
Requires-Dist: networkx (>=3.0,<4.0)
Requires-Dist: numba (>=0.56,<0.57)
Requires-Dist: numpy (>=1.22.3,<2.0.0)
Requires-Dist: pandas (>=1.4.1,<2.0.0)
Requires-Dist: regions (==0.7)
Requires-Dist: scipy (>=1.8.0,<2.0.0)
Requires-Dist: toml (>=0.10.2,<0.11.0)
Requires-Dist: tqdm (>=4.65,<5.0)
